MANIFEST.in
Makefile
README.rst
__init__.py
dev_req.txt
setup.cfg
setup.py
stati_net/__init__.py
stati_net/client.py
stati_net/exceptions.py
stati_net/http.py
stati_net/tcpip.py
stati_net/udp.py
stati_net.egg-info/PKG-INFO
stati_net.egg-info/SOURCES.txt
stati_net.egg-info/dependency_links.txt
stati_net.egg-info/requires.txt
stati_net.egg-info/top_level.txt